Metadata-Version: 1.2
Name: ECS-demo
Version: 0.0.dev0
Summary: ECS_demo: Pythonic analysis demo
Home-page: http://github.com/wesleybeckner/ECS/ECS
Author: Wesley Beckner
Author-email: wab665@uw.edu
License: MIT
Platform: OS Independent
Classifier: Development Status :: 3 - Alpha
Classifier: Environment :: Console
Classifier: Intended Audience :: Science/Research
Classifier: License :: OSI Approved :: MIT License
Classifier: Operating System :: OS Independent
Classifier: Programming Language :: Python :: 3.6
Classifier: Topic :: Scientific/Engineering
Requires: numpy
Requires-Python: ~=3.6
